dask_grblas/__init__.py
dask_grblas/_version.py
dask_grblas/base.py
dask_grblas/construction.py
dask_grblas/expr.py
dask_grblas/mask.py
dask_grblas/matrix.py
dask_grblas/scalar.py
dask_grblas/utils.py
dask_grblas/vector.py
dask_grblas-0.0.1.dist-info/LICENSE
dask_grblas-0.0.1.dist-info/METADATA
dask_grblas-0.0.1.dist-info/WHEEL
dask_grblas-0.0.1.dist-info/top_level.txt
dask_grblas-0.0.1.dist-info/RECORD
